README.md
setup.cfg
setup.py
opencvzone/FPS.py
opencvzone/FaceDetectionModule.py
opencvzone/FaceMeshModule.py
opencvzone/HandTrackingModule.py
opencvzone/PoseModule.py
opencvzone/SerialModule.py
opencvzone/Utils.py
opencvzone/__init__.py
opencvzone.egg-info/PKG-INFO
opencvzone.egg-info/SOURCES.txt
opencvzone.egg-info/dependency_links.txt
opencvzone.egg-info/requires.txt
opencvzone.egg-info/top_level.txt